Workbook

Sheet Overview
A1: FINANCIAL STATEMENT ANALYSIS — INDIA MEDIA INDUSTRY
A2: FY2020 to FY2024 | All figures in INR Crore | Source: StockAnalysis.com / S&P Global / Company Annual Reports
A4: Company | B4: Tier | C4: NSE Ticker | D4: FY2024 Revenue (₹ Cr)
A5: Zee Entertainment Enterprises Ltd | B5: Leader | C5: ZEEL | D5: 8,767
A6: Jagran Prakashan Ltd | B6: Mid-size | C6: JAGRAN | D6: 1,934
A7: D.B. Corp Ltd (Dainik Bhaskar) | B7: Underdog | C7: DBCORP | D7: 2,407
A9: INDUSTRY OVERVIEW
A10: India's digital media industry is going through a structural shift. Print is declining, OTT and digital news are growing fast and advertising money is following eyeballs online. The sector has three distinct tiers — large conglomerates with diversified revenue, mid-size players building digital-first models, and smaller challengers surviving on niche content or subscriptions.
A11: 1. LEADER — Zee Entertainment Enterprises Ltd (NSE: ZEEL)
A12: Listed on NSE/BSE. One of India's largest media conglomerates with digital arm ZEE5. Five years of clean audited financials available. Revenue scale, debt history and the Sony merger saga make it rich territory for red flag analysis. Profitability ratios moved significantly — good for interpretation.
A14: 2. MID-SIZE — Jagran Prakashan Ltd (NSE: JAGRAN)
A15: Listed company, primarily print but has a meaningful and growing digital presence. Revenue is stable enough to show efficiency ratios clearly but the print-to-digital transition creates interesting margin pressure — good for DuPont trend work.
A17: 3. UNDERDOG — D.B. Corp Ltd / Dainik Bhaskar (NSE: DBCORP)
A18: Also listed. Runs Dainik Bhaskar which is print-heavy but has been aggressively pushing digital. Smaller market cap, operates in competitive regional markets. Cash flow vs profit dynamics here are genuinely interesting. Data fully available on BSE and Screener.
A21: NOTES & DATA CONVENTIONS
A22: • All values in INR Crore (1 Crore = 10 million INR). Data converted from millions INR to Crore by dividing by 10.
A23: • FY2020 data not available (source covers FY2021 onwards). Marked as N/A. Verify from BSE annual reports.
A24: • EBIT = Operating Income as reported. EBT = Pretax Income as reported. Net Profit = Net Income to Common.
... A28: • Blue text = hardcoded inputs. Black text = formulas. Green text = cross-sheet references.

Sheet ZEEL
A1: Zee Entertainment Enterprises Ltd | Leader | NSE: ZEEL
A2: Financial Statement Analysis — FY2020 to FY2024 | Values in INR Crore
A3: Metric | B3: FY2020 | C3: FY2021 | D3: FY2022 | E3: FY2023 | F3: FY2024 | G3: 5Y CAGR (FY20→FY24)
A4: INCOME STATEMENT
A5: Revenue (₹ Cr) | B5: N/A | C5: 7729.9 | D5: 8305.8 | E5: 8167.6 | F5: 8766.5 | G5: =(F5/C5)^(1/3)-1 -> 0.042839455
A6: EBIT — Operating Income | B6: N/A | C6: 2117.3 | D6: 1679.2 | E6: 868.1 | F6: 727.4 | G6: =(F6/C6)^(1/3)-1 -> -0.29962554
A7: EBT — Pretax Income | B7: N/A | C7: 1255.6 | D7: 1498.5 | E7: 468.1 | F7: 381.1 | G7: =(F7/C7)^(1/3)-1 -> -0.32795883
A8: Net Profit | B8: N/A | C8: 800.1 | D8: 964.6 | E8: 47.8 | F8: 141.4 | G8: =(F8/C8)^(1/3)-1 -> -0.43882061
A9: BALANCE SHEET
A10: Total Assets (₹ Cr) | B10: N/A | C10: 12818.7 | D10: 13239.6 | E10: 13728.3 | F10: 13449.7 | G10: =(F10/C10)^(1/3)-1 -> 0.016146217
A11: Equity (₹ Cr) | B11: N/A | C11: 10110 | D11: 10865.2 | E11: 10721.9 | F11: 10875.3 | G11: =(F11/C11)^(1/3)-1 -> 0.024621261
A12: Debt (₹ Cr) | B12: N/A | C12: 423.1 | D12: 76.3 | E12: 282 | F12: 181 | G12: =(F12/C12)^(1/3)-1 -> -0.24650822
A13: REVENUE YEAR-ON-YEAR GROWTH
A14: YoY Revenue Growth (%) | B14: N/A | C14: N/A | D14: =(D5-C5)/C5 -> 0.074502904 | E14: =(E5-D5)/D5 -> -0.016638975 | F14: =(F5-E5)/E5 -> 0.073326314 | G14: —
A16: Source: StockAnalysis.com (S&P Global Market Intelligence) | Company Annual Reports on BSE | FY2020 data to be verified from BSE filings.

Sheet JAGRAN
A1: Jagran Prakashan Ltd | Mid-size | NSE: JAGRAN
A2: Financial Statement Analysis — FY2020 to FY2024 | Values in INR Crore
A3: Metric | B3: FY2020 | C3: FY2021 | D3: FY2022 | E3: FY2023 | F3: FY2024 | G3: 5Y CAGR (FY20→FY24)
A4: INCOME STATEMENT
A5: Revenue (₹ Cr) | B5: N/A | C5: 1289.2 | D5: 1616 | E5: 1856.2 | F5: 1933.9 | G5: =(F5/C5)^(1/3)-1 -> 0.14473397
A6: EBIT — Operating Income | B6: N/A | C6: 99.6 | D6: 241.1 | E6: 220.3 | F6: 256.7 | G6: =(F6/C6)^(1/3)-1 -> 0.371057
A7: EBT — Pretax Income | B7: N/A | C7: 107.2 | D7: 282.2 | E7: 253.2 | F7: 222.9 | G7: =(F7/C7)^(1/3)-1 -> 0.27635581
A8: Net Profit | B8: N/A | C8: 88.9 | D8: 222.5 | E8: 199.8 | F8: 183.7 | G8: =(F8/C8)^(1/3)-1 -> 0.27370582
A9: BALANCE SHEET
A10: Total Assets (₹ Cr) | B10: N/A | C10: 2988 | D10: 3174.9 | E10: 2957.9 | F10: 2850.9 | G10: =(F10/C10)^(1/3)-1 -> -0.015534585
A11: Equity (₹ Cr) | B11: N/A | C11: 2215.3 | D11: 2354.7 | E11: 2130.5 | F11: 2092.6 | G11: =(F11/C11)^(1/3)-1 -> -0.018814267
A12: Debt (₹ Cr) | B12: N/A | C12: 41.2 | D12: 54.5 | E12: 198.9 | F12: 86 | G12: =(F12/C12)^(1/3)-1 -> 0.27800851
A13: REVENUE YEAR-ON-YEAR GROWTH
A14: YoY Revenue Growth (%) | B14: N/A | C14: N/A | D14: =(D5-C5)/C5 -> 0.25349054 | E14: =(E5-D5)/D5 -> 0.14863861 | F14: =(F5-E5)/E5 -> 0.041859713 | G14: —
A16: Source: StockAnalysis.com (S&P Global Market Intelligence) | Company Annual Reports on BSE | FY2020 data to be verified from BSE filings.

Sheet DBCORP
A1: D.B. Corp Ltd (Dainik Bhaskar) | Underdog | NSE: DBCORP
A2: Financial Statement Analysis — FY2020 to FY2024 | Values in INR Crore
A3: Metric | B3: FY2020 | C3: FY2021 | D3: FY2022 | E3: FY2023 | F3: FY2024 | G3: 5Y CAGR (FY20→FY24)
A4: INCOME STATEMENT
A5: Revenue (₹ Cr) | B5: N/A | C5: 1509.6 | D5: 1770.3 | E5: 2131.9 | F5: 2407.2 | G5: =(F5/C5)^(1/3)-1 -> 0.16828848
A6: EBIT — Operating Income | B6: N/A | C6: 192.8 | D6: 202.4 | E6: 224.9 | F6: 524.1 | G6: =(F6/C6)^(1/3)-1 -> 0.39562597
A7: EBT — Pretax Income | B7: N/A | C7: 193.2 | D7: 194.7 | E7: 227.9 | F7: 565.5 | G7: =(F7/C7)^(1/3)-1 -> 0.43045817
A8: Net Profit | B8: N/A | C8: 141.4 | D8: 142.6 | E8: 169.1 | F8: 425.5 | G8: =(F8/C8)^(1/3)-1 -> 0.44372137
A9: BALANCE SHEET
A10: Total Assets (₹ Cr) | B10: N/A | C10: 2476 | D10: 2536.9 | E10: 2578.8 | F10: 2992.7 | G10: =(F10/C10)^(1/3)-1 -> 0.065215591
A11: Equity (₹ Cr) | B11: N/A | C11: 1822.9 | D11: 1887.5 | E11: 1944.7 | F11: 2224.6 | G11: =(F11/C11)^(1/3)-1 -> 0.068635743
A12: Debt (₹ Cr) | B12: N/A | C12: 56.3 | D12: 22.6 | E12: 32.5 | F12: 22.5 | G12: =(F12/C12)^(1/3)-1 -> -0.26341188
A13: REVENUE YEAR-ON-YEAR GROWTH
A14: YoY Revenue Growth (%) | B14: N/A | C14: N/A | D14: =(D5-C5)/C5 -> 0.17269475 | E14: =(E5-D5)/D5 -> 0.20425917 | F14: =(F5-E5)/E5 -> 0.12913364 | G14: —
A16: Source: StockAnalysis.com (S&P Global Market Intelligence) | Company Annual Reports on BSE | FY2020 data to be verified from BSE filings.

Sheet Comparison
A1: CONSOLIDATED COMPARISON — ALL 3 COMPANIES
A2: FY2021 to FY2024 | INR Crore | FY2020 excluded (data not available)
A3: Metric / Company | B3: FY2021 | C3: FY2022 | D3: FY2023 | E3: FY2024
A4: REVENUE (₹ Crore)
A5: Zee Entertainment | B5: =ZEEL!C5 -> 7729.9 | C5: =ZEEL!D5 -> 8305.8 | D5: =ZEEL!E5 -> 8167.6 | E5: =ZEEL!F5 -> 8766.5
A6: Jagran Prakashan | B6: =JAGRAN!C5 -> 1289.2 | C6: =JAGRAN!D5 -> 1616 | D6: =JAGRAN!E5 -> 1856.2 | E6: =JAGRAN!F5 -> 1933.9
A7: DB Corp | B7: =DBCORP!C5 -> 1509.6 | C7: =DBCORP!D5 -> 1770.3 | D7: =DBCORP!E5 -> 2131.9 | E7: =DBCORP!F5 -> 2407.2
A9: NET PROFIT (₹ Crore)
A10: Zee Entertainment | B10: =ZEEL!C8 -> 800.1 | C10: =ZEEL!D8 -> 964.6 | D10: =ZEEL!E8 -> 47.8 | E10: =ZEEL!F8 -> 141.4
A11: Jagran Prakashan | B11: =JAGRAN!C8 -> 88.9 | C11: =JAGRAN!D8 -> 222.5 | D11: =JAGRAN!E8 -> 199.8 | E11: =JAGRAN!F8 -> 183.7
A12: DB Corp | B12: =DBCORP!C8 -> 141.4 | C12: =DBCORP!D8 -> 142.6 | D12: =DBCORP!E8 -> 169.1 | E12: =DBCORP!F8 -> 425.5
A14: TOTAL ASSETS (₹ Crore)
A15: Zee Entertainment | B15: =ZEEL!C10 -> 12818.7 | C15: =ZEEL!D10 -> 13239.6 | D15: =ZEEL!E10 -> 13728.3 | E15: =ZEEL!F10 -> 13449.7
A16: Jagran Prakashan | B16: =JAGRAN!C10 -> 2988 | C16: =JAGRAN!D10 -> 3174.9 | D16: =JAGRAN!E10 -> 2957.9 | E16: =JAGRAN!F10 -> 2850.9
A17: DB Corp | B17: =DBCORP!C10 -> 2476 | C17: =DBCORP!D10 -> 2536.9 | D17: =DBCORP!E10 -> 2578.8 | E17: =DBCORP!F10 -> 2992.7
A19: EQUITY (₹ Crore)
A20: Zee Entertainment | B20: =ZEEL!C11 -> 10110 | C20: =ZEEL!D11 -> 10865.2 | D20: =ZEEL!E11 -> 10721.9 | E20: =ZEEL!F11 -> 10875.3
A21: Jagran Prakashan | B21: =JAGRAN!C11 -> 2215.3 | C21: =JAGRAN!D11 -> 2354.7 | D21: =JAGRAN!E11 -> 2130.5 | E21: =JAGRAN!F11 -> 2092.6
A22: DB Corp | B22: =DBCORP!C11 -> 1822.9 | C22: =DBCORP!D11 -> 1887.5 | D22: =DBCORP!E11 -> 1944.7 | E22: =DBCORP!F11 -> 2224.6
A24: DEBT (₹ Crore)
A25: Zee Entertainment | B25: =ZEEL!C12 -> 423.1 | C25: =ZEEL!D12 -> 76.3 | D25: =ZEEL!E12 -> 282 | E25: =ZEEL!F12 -> 181
A26: Jagran Prakashan | B26: =JAGRAN!C12 -> 41.2 | C26: =JAGRAN!D12 -> 54.5 | D26: =JAGRAN!E12 -> 198.9 | E26: =JAGRAN!F12 -> 86
A27: DB Corp | B27: =DBCORP!C12 -> 56.3 | C27: =DBCORP!D12 -> 22.6 | D27: =DBCORP!E12 -> 32.5 | E27: =DBCORP!F12 -> 22.5

Sheet Ratio Analysis
A1: RATIO ANALYSIS — INDIA MEDIA INDUSTRY | FY2021–FY2024 | INR Crore
A2: Color Convention: Blue = Hardcoded inputs | Black = Formulas | Green = Cross-sheet references
B3: ZEE ENTERTAINMENT (ZEEL) | F3: JAGRAN PRAKASHAN | J3: DB CORP (DBCORP) | O3: INTERPRETATION
A4: Ratio | B4: FY2021 | C4: FY2022 | D4: FY2023 | E4: FY2024 | F4: FY2021 | G4: FY2022 | H4: FY2023 | I4: FY2024 | J4: FY2021 | K4: FY2022 | L4: FY2023 | M4: FY2024 | O4: Root Cause & Analysis
A5: PROFITABILITY RATIOS
A6: EBIT Margin | B6: =ZEEL!C6/ZEEL!C5 -> 0.2739104 | C6: =ZEEL!D6/ZEEL!D5 -> 0.20217198 | D6: =ZEEL!E6/ZEEL!E5 -> 0.10628581 | E6: =ZEEL!F6/ZEEL!F5 -> 0.082974962 | F6: =JAGRAN!C6/JAGRAN!C5 -> 0.077257214 | G6: =JAGRAN!D6/JAGRAN!D5 -> 0.14919554 | H6: =JAGRAN!E6/JAGRAN!E5 -> 0.11868333 | I6: =JAGRAN!F6/JAGRAN!F5 -> 0.13273696 | J6: =DBCORP!C6/DBCORP!C5 -> 0.12771595 | K6: =DBCORP!D6/DBCORP!D5 -> 0.1143309 | L6: =DBCORP!E6/DBCORP!E5 -> 0.10549275 | M6: =DBCORP!F6/DBCORP!F5 -> 0.21772183 | O6: ZEEL: Collapsed 27.4%→8.3%. Root cause: Failed Sony merger (CCI blocked Jan 2024) created massive legal costs + OTT competition (JioCinema, Hotstar) eroded ad revenue. JAGRAN: Recovered 7.7%→13.3%. Print ad bounce post-COVID + newsprint cost stabilisation. DBCORP: Best performer 12.8%→21.8%. Regional market dominance shielded from OTT pressure; newsprint costs fell from FY23 peak.
A7: Net Profit Margin | B7: =ZEEL!C8/ZEEL!C5 -> 0.10350716 | C7: =ZEEL!D8/ZEEL!D5 -> 0.11613571 | D7: =ZEEL!E8/ZEEL!E5 -> 0.0058523924 | E7: =ZEEL!F8/ZEEL!F5 -> 0.016129584 | F7: =JAGRAN!C8/JAGRAN!C5 -> 0.068957493 | G7: =JAGRAN!D8/JAGRAN!D5 -> 0.13768564 | H7: =JAGRAN!E8/JAGRAN!E5 -> 0.10763926 | I7: =JAGRAN!F8/JAGRAN!F5 -> 0.0949894 | J7: =DBCORP!C8/DBCORP!C5 -> 0.093667197 | K7: =DBCORP!D8/DBCORP!D5 -> 0.080551319 | L7: =DBCORP!E8/DBCORP!E5 -> 0.079318917 | M7: =DBCORP!F8/DBCORP!F5 -> 0.17676138 | O7: ZEEL: Freefall 10.3%→1.6%. FY23 near-breakeven due to Sony merger costs + ZEE5 content impairment charges. JAGRAN: Healthy recovery 6.9%→9.5%. Print ad recovery + cost control offset digital drag. DBCORP: Most dramatic turnaround 9.4%→17.7%. FY24: ₹425 Cr net profit vs ₹141 Cr in FY21. Ad volume recovery + newsprint tailwind + zero M&A distraction.
A8: EBT Margin | B8: =ZEEL!C7/ZEEL!C5 -> 0.16243418 | C8: =ZEEL!D7/ZEEL!D5 -> 0.18041609 | D8: =ZEEL!E7/ZEEL!E5 -> 0.057311817 | E8: =ZEEL!F7/ZEEL!F5 -> 0.043472309 | F8: =JAGRAN!C7/JAGRAN!C5 -> 0.083152343 | G8: =JAGRAN!D7/JAGRAN!D5 -> 0.17462871 | H8: =JAGRAN!E7/JAGRAN!E5 -> 0.13640771 | I8: =JAGRAN!F7/JAGRAN!F5 -> 0.11525932 | J8: =DBCORP!C7/DBCORP!C5 -> 0.12798092 | K8: =DBCORP!D7/DBCORP!D5 -> 0.10998136 | L8: =DBCORP!E7/DBCORP!E5 -> 0.10689995 | M8: =DBCORP!F7/DBCORP!F5 -> 0.23492024 | O8: ZEEL: Declined 16.2%→4.3%, reflecting both operating pressure AND below-EBIT hits (investment losses, forex, impairments). JAGRAN: Improved 8.3%→11.5%, aided by other income contributions and lower interest costs. DBCORP: Soared 12.8%→23.5% — above EBIT margin, indicating treasury/investment income also contributed positively in FY24.
A9: Return on Assets | B9: =ZEEL!C8/ZEEL!C10 -> 0.062416626 | C9: =ZEEL!D8/ZEEL!D10 -> 0.072857186 | D9: =ZEEL!E8/ZEEL!E10 -> 0.0034818586 | E9: =ZEEL!F8/ZEEL!F10 -> 0.010513246 | F9: =JAGRAN!C8/JAGRAN!C10 -> 0.029752343 | G9: =JAGRAN!D8/JAGRAN!D10 -> 0.070080947 | H9: =JAGRAN!E8/JAGRAN!E10 -> 0.067547923 | I9: =JAGRAN!F8/JAGRAN!F10 -> 0.064435792 | J9: =DBCORP!C8/DBCORP!C10 -> 0.057108239 | K9: =DBCORP!D8/DBCORP!D10 -> 0.056210335 | L9: =DBCORP!E8/DBCORP!E10 -> 0.065573135 | M9: =DBCORP!F8/DBCORP!F10 -> 0.1421793 | O9: ZEEL: Collapsed 6.2%→1.1%. Assets grew (content+tech) but profits crashed — ROA destruction. JAGRAN: Improved 3.0%→6.4%. Leaner asset base (₹2988→₹2851 Cr) while profits stayed strong = efficient asset use. DBCORP: Jumped 5.7%→14.2%. Best ROA trajectory. Asset base grew (₹2476→₹2993 Cr) but profit grew faster. Clear winner in asset productivity.
A10: Return on Equity | B10: =ZEEL!C8/ZEEL!C11 -> 0.079139466 | C10: =ZEEL!D8/ZEEL!D11 -> 0.088778854 | D10: =ZEEL!E8/ZEEL!E11 -> 0.0044581651 | E10: =ZEEL!F8/ZEEL!F11 -> 0.01300194 | F10: =JAGRAN!C8/JAGRAN!C11 -> 0.040130005 | G10: =JAGRAN!D8/JAGRAN!D11 -> 0.094491867 | H10: =JAGRAN!E8/JAGRAN!E11 -> 0.093780803 | I10: =JAGRAN!F8/JAGRAN!F11 -> 0.08778553 | J10: =DBCORP!C8/DBCORP!C11 -> 0.077568709 | K10: =DBCORP!D8/DBCORP!D11 -> 0.075549669 | L10: =DBCORP!E8/DBCORP!E11 -> 0.086954286 | M10: =DBCORP!F8/DBCORP!F11 -> 0.19127034 | O10: ZEEL: Fell sharply 7.9%→1.3%. Equity base stable (~₹10,800 Cr) but profits near zero — shareholders barely earned above bank FD rates. JAGRAN: Rose 4.0%→8.8%. Consistent improvement; equity shrank slightly (buybacks/dividends) while profits held. DBCORP: Skyrocketed 7.8%→19.1%. Equity grew moderately but profit tripled. Investors rewarded significantly.
A11: Asset Turnover | B11: =ZEEL!C5/ZEEL!C10 -> 0.60301747 | C11: =ZEEL!D5/ZEEL!D10 -> 0.62734524 | D11: =ZEEL!E5/ZEEL!E10 -> 0.59494621 | E11: =ZEEL!F5/ZEEL!F10 -> 0.65179892 | F11: =JAGRAN!C5/JAGRAN!C10 -> 0.43145917 | G11: =JAGRAN!D5/JAGRAN!D10 -> 0.50899241 | H11: =JAGRAN!E5/JAGRAN!E10 -> 0.62753981 | I11: =JAGRAN!F5/JAGRAN!F10 -> 0.67834719 | J11: =DBCORP!C5/DBCORP!C10 -> 0.60969305 | K11: =DBCORP!D5/DBCORP!D10 -> 0.69782017 | L11: =DBCORP!E5/DBCORP!E10 -> 0.82670234 | M11: =DBCORP!F5/DBCORP!F10 -> 0.80435727 | O11: ZEEL: Low 0.60–0.65x — large content library + goodwill inflate assets relative to revenue. JAGRAN: Improved 0.43x→0.68x. Shrinking asset base + growing revenue = significant efficiency gain; non-core assets disposed. DBCORP: Rising 0.61x→0.80x. Best and improving. Lean balance sheet + strong revenue growth. Operational efficiency leader.
A13: SOLVENCY / LEVERAGE RATIOS
A14: Debt-to-Equity | B14: =ZEEL!C12/ZEEL!C11 -> 0.041849654 | C14: =ZEEL!D12/ZEEL!D11 -> 0.0070224202 | D14: =ZEEL!E12/ZEEL!E11 -> 0.026301309 | E14: =ZEEL!F12/ZEEL!F11 -> 0.016643219 | F14: =JAGRAN!C12/JAGRAN!C11 -> 0.018597933 | G14: =JAGRAN!D12/JAGRAN!D11 -> 0.023145199 | H14: =JAGRAN!E12/JAGRAN!E11 -> 0.093358367 | I14: =JAGRAN!F12/JAGRAN!F11 -> 0.0410972 | J14: =DBCORP!C12/DBCORP!C11 -> 0.030884854 | K14: =DBCORP!D12/DBCORP!D11 -> 0.01197351 | L14: =DBCORP!E12/DBCORP!E11 -> 0.016712089 | M14: =DBCORP!F12/DBCORP!F11 -> 0.010114178 | O14: ZEEL: ~0.04x in FY21 (near debt-free) → 0.017x FY24. FY23 spike to 0.026x due to short-term borrowings during merger uncertainty. JAGRAN: Rose worryingly 0.02x→0.09x FY23 (digital capex), reduced to 0.04x FY24 — prudent deleveraging. DBCORP: Near debt-free; fell 0.03x→0.01x. Strong internal cash generation. Zero external borrowing = excellent financial discipline.
A15: Debt-to-Assets | B15: =ZEEL!C12/ZEEL!C10 -> 0.033006467 | C15: =ZEEL!D12/ZEEL!D10 -> 0.005763014 | D15: =ZEEL!E12/ZEEL!E10 -> 0.020541509 | E15: =ZEEL!F12/ZEEL!F10 -> 0.013457549 | F15: =JAGRAN!C12/JAGRAN!C10 -> 0.013788487 | G15: =JAGRAN!D12/JAGRAN!D10 -> 0.017165895 | H15: =JAGRAN!E12/JAGRAN!E10 -> 0.067243653 | I15: =JAGRAN!F12/JAGRAN!F10 -> 0.030165913 | J15: =DBCORP!C12/DBCORP!C10 -> 0.022738288 | K15: =DBCORP!D12/DBCORP!D10 -> 0.0089085104 | L15: =DBCORP!E12/DBCORP!E10 -> 0.012602761 | M15: =DBCORP!F12/DBCORP!F10 -> 0.0075182945 | O15: ZEEL: Stable low 0.01–0.03x. Pristine balance sheet on leverage metric. JAGRAN: Spiked FY23 (0.07x) — temporary digital investment phase; normalised FY24. DBCORP: Negligible across all years (0.008x FY24). Revenue grew strongly while debt almost vanished. Most sustainable revenue-to-debt profile.
A16: Equity Ratio | B16: =ZEEL!C11/ZEEL!C10 -> 0.78869152 | C16: =ZEEL!D11/ZEEL!D10 -> 0.82065923 | D16: =ZEEL!E11/ZEEL!E10 -> 0.78100712 | E16: =ZEEL!F11/ZEEL!F10 -> 0.80859053 | F16: =JAGRAN!C11/JAGRAN!C10 -> 0.74139893 | G16: =JAGRAN!D11/JAGRAN!D10 -> 0.74166115 | H16: =JAGRAN!E11/JAGRAN!E10 -> 0.72027452 | I16: =JAGRAN!F11/JAGRAN!F10 -> 0.73401382 | J16: =DBCORP!C11/DBCORP!C10 -> 0.73622779 | K16: =DBCORP!D11/DBCORP!D10 -> 0.74401829 | L16: =DBCORP!E11/DBCORP!E10 -> 0.75411044 | M16: =DBCORP!F11/DBCORP!F10 -> 0.74334213 | O16: ZEEL: Consistently high 78–82%. Self-funded company. JAGRAN: Dropped slightly 74%→73% due to debt pickup, but still very equity-heavy. DBCORP: Improved 73.6%→74.3%. Equity base growing (retained profits) while assets also grow. Sustainably capitalised.
A17: Interest Coverage | B17: =IFERROR(ZEEL!C6/(ZEEL!C6-ZEEL!C7),"-") -> 2.4571196 | C17: =IFERROR(ZEEL!D6/(ZEEL!D6-ZEEL!D7),"-") -> 9.2927504 | D17: =IFERROR(ZEEL!E6/(ZEEL!E6-ZEEL!E7),"-") -> 2.17025 | E17: =IFERROR(ZEEL!F6/(ZEEL!F6-ZEEL!F7),"-") -> 2.1004909 | F17: =IFERROR(JAGRAN!C6/(JAGRAN!C6-JAGRAN!C7),"-") -> -13.105263 | G17: =IFERROR(JAGRAN!D6/(JAGRAN!D6-JAGRAN!D7),"-") -> -5.86618 | H17: =IFERROR(JAGRAN!E6/(JAGRAN!E6-JAGRAN!E7),"-") -> -6.6960486 | I17: =IFERROR(JAGRAN!F6/(JAGRAN!F6-JAGRAN!F7),"-") -> 7.5946746 | J17: =IFERROR(DBCORP!C6/(DBCORP!C6-DBCORP!C7),"-") -> -482 | K17: =IFERROR(DBCORP!D6/(DBCORP!D6-DBCORP!D7),"-") -> 26.285714 | L17: =IFERROR(DBCORP!E6/(DBCORP!E6-DBCORP!E7),"-") -> -74.966667 | M17: =IFERROR(DBCORP!F6/(DBCORP!F6-DBCORP!F7),"-") -> -12.65942 | O17: Note: Implicit interest = EBIT − EBT. ZEEL: Coverage compressed as EBIT fell; below-line charges from failed Sony merger widened gap. JAGRAN: Comfortable coverage by FY24 — EBIT grew faster than interest costs. DBCORP: Very high coverage — FY24 EBIT ₹524 Cr vs minimal debt costs. Near-zero interest burden reinforces financial strength.
A18: Debt-to-Revenue | B18: =ZEEL!C12/ZEEL!C5 -> 0.054735508 | C18: =ZEEL!D12/ZEEL!D5 -> 0.0091863517 | D18: =ZEEL!E12/ZEEL!E5 -> 0.034526666 | E18: =ZEEL!F12/ZEEL!F5 -> 0.02064678 | F18: =JAGRAN!C12/JAGRAN!C5 -> 0.031957803 | G18: =JAGRAN!D12/JAGRAN!D5 -> 0.033725248 | H18: =JAGRAN!E12/JAGRAN!E5 -> 0.1071544 | I18: =JAGRAN!F12/JAGRAN!F5 -> 0.044469724 | J18: =DBCORP!C12/DBCORP!C5 -> 0.037294648 | K18: =DBCORP!D12/DBCORP!D5 -> 0.012766198 | L18: =DBCORP!E12/DBCORP!E5 -> 0.015244617 | M18: =DBCORP!F12/DBCORP!F5 -> 0.0093469591 | O18: ZEEL: Low 0.02–0.03x but slightly rising relative to revenue trends. JAGRAN: Spike FY23 (0.11x) — debt funded digital/capex but revenue growth absorbed it back to 0.04x FY24. DBCORP: Negligible (0.009x FY24). Revenue grew strongly while debt almost vanished. Most sustainable profile in cohort.
A20: EFFICIENCY RATIOS
A21: Revenue per Asset | B21: =ZEEL!C5/ZEEL!C10 -> 0.60301747 | C21: =ZEEL!D5/ZEEL!D10 -> 0.62734524 | D21: =ZEEL!E5/ZEEL!E10 -> 0.59494621 | E21: =ZEEL!F5/ZEEL!F10 -> 0.65179892 | F21: =JAGRAN!C5/JAGRAN!C10 -> 0.43145917 | G21: =JAGRAN!D5/JAGRAN!D10 -> 0.50899241 | H21: =JAGRAN!E5/JAGRAN!E10 -> 0.62753981 | I21: =JAGRAN!F5/JAGRAN!F10 -> 0.67834719 | J21: =DBCORP!C5/DBCORP!C10 -> 0.60969305 | K21: =DBCORP!D5/DBCORP!D10 -> 0.69782017 | L21: =DBCORP!E5/DBCORP!E10 -> 0.82670234 | M21: =DBCORP!F5/DBCORP!F10 -> 0.80435727 | O21: Identical to Asset Turnover. DBCORP leads at 0.80x; ZEEL lags at 0.65x due to heavy content assets. JAGRAN mid-tier at 0.68x but best trajectory (was 0.43x in FY21 — massive efficiency gain over 4 years).
A22: Equity Multiplier | B22: =ZEEL!C10/ZEEL!C11 -> 1.2679228 | C22: =ZEEL!D10/ZEEL!D11 -> 1.2185326 | D22: =ZEEL!E10/ZEEL!E11 -> 1.2803981 | E22: =ZEEL!F10/ZEEL!F11 -> 1.2367199 | F22: =JAGRAN!C10/JAGRAN!C11 -> 1.3488015 | G22: =JAGRAN!D10/JAGRAN!D11 -> 1.3483246 | H22: =JAGRAN!E10/JAGRAN!E11 -> 1.3883595 | I22: =JAGRAN!F10/JAGRAN!F11 -> 1.3623722 | J22: =DBCORP!C10/DBCORP!C11 -> 1.3582753 | K22: =DBCORP!D10/DBCORP!D11 -> 1.344053 | L22: =DBCORP!E10/DBCORP!E11 -> 1.3260657 | M22: =DBCORP!F10/DBCORP!F11 -> 1.3452756 | O22: All three are low-multiplier companies (1.2–1.35x) = conservative, equity-financed. ZEEL: 1.24x FY24 — very low leverage. JAGRAN: 1.36x — slightly higher due to debt pickup. DBCORP: 1.35x — well-managed. Low multiplier is GOOD for media companies with volatile advertising revenue cycles.
A24: GROWTH RATIOS (Year-on-Year %)
A25: Revenue Growth | B25: N/A | C25: =(ZEEL!D5-ZEEL!C5)/ZEEL!C5 -> 0.074502904 | D25: =(ZEEL!E5-ZEEL!D5)/ZEEL!D5 -> -0.016638975 | E25: =(ZEEL!F5-ZEEL!E5)/ZEEL!E5 -> 0.073326314 | F25: N/A | G25: =(JAGRAN!D5-JAGRAN!C5)/JAGRAN!C5 -> 0.25349054 | H25: =(JAGRAN!E5-JAGRAN!D5)/JAGRAN!D5 -> 0.14863861 | I25: =(JAGRAN!F5-JAGRAN!E5)/JAGRAN!E5 -> 0.041859713 | J25: N/A | K25: =(DBCORP!D5-DBCORP!C5)/DBCORP!C5 -> 0.17269475 | L25: =(DBCORP!E5-DBCORP!D5)/DBCORP!D5 -> 0.20425917 | M25: =(DBCORP!F5-DBCORP!E5)/DBCORP!E5 -> 0.12913364 | O25: ZEEL: Volatile. FY22: +7.5%, FY23: −1.7% (merger chaos), FY24: +7.3% — recovery. No consistent growth story. JAGRAN: Strong recovery. FY22: +25.3%, FY23: +14.9%, FY24: +4.2% — moderating but positive. Secular print concern. DBCORP: Consistent outperformer. FY22: +17.3%, FY23: +20.4%, FY24: +12.9%. Regional advertising market proved resilient. Best growth record.
A26: Net Profit Growth | B26: N/A | C26: =(ZEEL!D8-ZEEL!C8)/ABS(ZEEL!C8) -> 0.2055993 | D26: =(ZEEL!E8-ZEEL!D8)/ABS(ZEEL!D8) -> -0.95044578 | E26: =(ZEEL!F8-ZEEL!E8)/ABS(ZEEL!E8) -> 1.958159 | F26: N/A | G26: =(JAGRAN!D8-JAGRAN!C8)/ABS(JAGRAN!C8) -> 1.5028121 | H26: =(JAGRAN!E8-JAGRAN!D8)/ABS(JAGRAN!D8) -> -0.10202247 | I26: =(JAGRAN!F8-JAGRAN!E8)/ABS(JAGRAN!E8) -> -0.080580581 | J26: N/A | K26: =(DBCORP!D8-DBCORP!C8)/ABS(DBCORP!C8) -> 0.0084865629 | L26: =(DBCORP!E8-DBCORP!D8)/ABS(DBCORP!D8) -> 0.1858345 | M26: =(DBCORP!F8-DBCORP!E8)/ABS(DBCORP!E8) -> 1.5162626 | O26: ZEEL: Extremely volatile. FY22: +20.6%, FY23: −95.0% (near wipeout), FY24: +195.8% (recovery from low base). JAGRAN: FY22: +150.3% (post-COVID snap-back), FY23: −10.2%, FY24: −8.1% — profit sliding despite revenue growth. DBCORP: FY22: +0.8%, FY23: +18.6%, FY24: +151.6% — exceptional! Profit tripled in FY24. Operating leverage kicked in massively.
A27: EBIT Growth | B27: N/A | C27: =(ZEEL!D6-ZEEL!C6)/ABS(ZEEL!C6) -> -0.20691447 | D27: =(ZEEL!E6-ZEEL!D6)/ABS(ZEEL!D6) -> -0.48302763 | E27: =(ZEEL!F6-ZEEL!E6)/ABS(ZEEL!E6) -> -0.1620781 | F27: N/A | G27: =(JAGRAN!D6-JAGRAN!C6)/ABS(JAGRAN!C6) -> 1.4206827 | H27: =(JAGRAN!E6-JAGRAN!D6)/ABS(JAGRAN!D6) -> -0.086271257 | I27: =(JAGRAN!F6-JAGRAN!E6)/ABS(JAGRAN!E6) -> 0.16522923 | J27: N/A | K27: =(DBCORP!D6-DBCORP!C6)/ABS(DBCORP!C6) -> 0.049792531 | L27: =(DBCORP!E6-DBCORP!D6)/ABS(DBCORP!D6) -> 0.11116601 | M27: =(DBCORP!F6-DBCORP!E6)/ABS(DBCORP!E6) -> 1.3303691 | O27: ZEEL: FY22: −20.7%, FY23: −48.3%, FY24: −16.2% — structural operating profit decline. Content costs + lower ad yields. JAGRAN: FY22: +142.1%, FY23: −8.6%, FY24: +16.5% — FY24 recovery encouraging. DBCORP: FY22: +5.0%, FY23: +11.1%, FY24: +133.0% — explosive FY24 EBIT growth. Revenue scale + newsprint cost moderation = operating leverage realised.

Sheet DuPont_ZEEL
A1: 5-STEP DuPont ANALYSIS — Zee Entertainment Enterprises Ltd | Leader
A2: FY2021–FY2024 | ROE decomposed into 5 drivers | All formulas live — referencing source data sheets
A3: ROE = Tax Burden × Interest Burden × EBIT Margin × Asset Turnover × Equity Multiplier
A4: (Net Profit / EBT) × (EBT / EBIT) × (EBIT / Revenue) × (Revenue / Assets) × (Assets / Equity)
A5: DuPont Component | B5: FY2021 | C5: FY2022 | D5: FY2023 | E5: FY2024 | F5: 4Y Trend | H5: Interpretation
A6: ① Tax Burden (Net Profit / EBT) | B6: =ZEEL!C8/ZEEL!C7 -> 0.63722523 | C6: =ZEEL!D8/ZEEL!D7 -> 0.64371038 | D6: =ZEEL!E8/ZEEL!E7 -> 0.10211493 | E6: =ZEEL!F8/ZEEL!F7 -> 0.37103123 | F6: =(E6-B6)/ABS(B6) -> -0.41773927 | H6: Tax burden fell sharply in FY23 as lower EBT made effective tax rates appear volatile. Recovery in FY24 is modest — tax efficiency is a function of profitability scale rather than planning.
A7: ② Interest Burden (EBT / EBIT) | B7: =ZEEL!C7/ZEEL!C6 -> 0.59301941 | C7: =ZEEL!D7/ZEEL!D6 -> 0.89238923 | D7: =ZEEL!E7/ZEEL!E6 -> 0.53922359 | E7: =ZEEL!F7/ZEEL!F6 -> 0.52392081 | F7: =(E7-B7)/ABS(B7) -> -0.11651996 | H7: ZEEL's interest burden fell 0.59x→0.52x, indicating non-operating charges (write-offs, provisions from the failed Sony merger) are widening the gap between EBIT and EBT. A ratio below 1.0x captures more than just interest — it includes below-the-line charges eating into operating profit.
A8: ③ EBIT Margin (EBIT / Revenue) | B8: =ZEEL!C6/ZEEL!C5 -> 0.2739104 | C8: =ZEEL!D6/ZEEL!D5 -> 0.20217198 | D8: =ZEEL!E6/ZEEL!E5 -> 0.10628581 | E8: =ZEEL!F6/ZEEL!F5 -> 0.082974962 | F8: =(E8-B8)/ABS(B8) -> -0.69707261 | H8: EBIT margin is the single most important driver of ZEEL's ROE deterioration. Fell 27.4%→8.3% — a structural collapse. Content cost inflation, ZEE5 digital investment, and Sony merger disruption all contributed. This is the lever ZEEL must fix to restore meaningful ROE.
A9: ④ Asset Turnover (Revenue / Total Assets) | B9: =ZEEL!C5/ZEEL!C10 -> 0.60301747 | C9: =ZEEL!D5/ZEEL!D10 -> 0.62734524 | D9: =ZEEL!E5/ZEEL!E10 -> 0.59494621 | E9: =ZEEL!F5/ZEEL!F10 -> 0.65179892 | F9: =(E9-B9)/ABS(B9) -> 0.080895597 | H9: Asset turnover improved modestly 0.60x→0.65x. ZEEL's large content library and intangible asset base structurally limits turnover — assets grow as content is commissioned while revenue growth is uneven. FY24 improvement as assets contracted is a positive signal but insufficient to offset margin collapse.
A10: ⑤ Equity Multiplier (Total Assets / Equity) | B10: =ZEEL!C10/ZEEL!C11 -> 1.2679228 | C10: =ZEEL!D10/ZEEL!D11 -> 1.2185326 | D10: =ZEEL!E10/ZEEL!E11 -> 1.2803981 | E10: =ZEEL!F10/ZEEL!F11 -> 1.2367199 | F10: =(E10-B10)/ABS(B10) -> -0.024609496 | H10: Equity multiplier of ~1.24x reflects ZEEL's extremely conservative capital structure — almost entirely equity-funded. Low leverage is double-edged: it protects against distress but limits ROE amplification. A multiplier of 2.0x would double ZEEL's ROE without changing operating performance.
A11: ROE = ① × ② × ③ × ④ × ⑤ | B11: =B6*B7*B8*B9*B10 -> 0.079139466 | C11: =C6*C7*C8*C9*C10 -> 0.088778854 | D11: =D6*D7*D8*D9*D10 -> 0.0044581651 | E11: =E6*E7*E8*E9*E10 -> 0.01300194 | F11: =(E11-B11)/ABS(B11) -> -0.83570852 | H11: ZEEL's ROE collapsed 7.9%→0.4% (FY23) and barely recovered to 1.3% (FY24). DuPont makes the cause unambiguous: primary culprit is EBIT margin destruction (−19 pp). Asset turnover improved slightly and equity multiplier is stable. ZEEL needs margin recovery above all else — no amount of balance sheet restructuring fixes a business with 8% EBIT margins on a largely equity-funded capital base.
A13: ROE DRIVER ANALYSIS — Primary / Secondary / Negligible contribution to ROE change FY2021 → FY2024
A14: Driver | B14: Classification | D14: Commentary
A15: EBIT Margin | B15: PRIMARY DRIVER | D15: Fell from 27.4% to 8.3% — responsible for ~80% of ROE destruction. Content costs and digital transition costs are the core problem.
A16: Tax Burden | B16: SECONDARY | D16: Volatile due to low earnings base — not a structural driver in either direction.
A17: Interest Burden | B17: SECONDARY | D17: Below-the-line write-offs from merger widened EBT-EBIT gap. Needs monitoring.
A18: Asset Turnover | B18: MINOR POSITIVE | D18: Improved from 0.60x to 0.65x — the only consistent positive contributor.
A19: Equity Multiplier | B19: NEGLIGIBLE | D19: Stable at ~1.24x. Conservative structure limits both risk and ROE amplification.

Sheet DuPont_JAGRAN
A1: 5-STEP DuPont ANALYSIS — Jagran Prakashan Ltd | Mid-size
A2: FY2021–FY2024 | ROE decomposed into 5 drivers | All formulas live — referencing source data sheets
A3: ROE = Tax Burden × Interest Burden × EBIT Margin × Asset Turnover × Equity Multiplier
A4: (Net Profit / EBT) × (EBT / EBIT) × (EBIT / Revenue) × (Revenue / Assets) × (Assets / Equity)
A5: DuPont Component | B5: FY2021 | C5: FY2022 | D5: FY2023 | E5: FY2024 | F5: 4Y Trend | H5: Interpretation
A6: ① Tax Burden (Net Profit / EBT) | B6: =JAGRAN!C8/JAGRAN!C7 -> 0.82929104 | C6: =JAGRAN!D8/JAGRAN!D7 -> 0.78844791 | D6: =JAGRAN!E8/JAGRAN!E7 -> 0.78909953 | E6: =JAGRAN!F8/JAGRAN!F7 -> 0.82413638 | F6: =(E6-B6)/ABS(B6) -> -0.0062157439 | H6: Jagran's tax burden is consistent in the 0.79–0.82x range, reflecting a stable effective tax rate under normal operating conditions. The spike toward 0.8x in FY22 reflects strong pre-tax profits taxed at the standard corporate rate with limited deferred tax benefits.
A7: ② Interest Burden (EBT / EBIT) | B7: =JAGRAN!C7/JAGRAN!C6 -> 1.0763052 | C7: =JAGRAN!D7/JAGRAN!D6 -> 1.1704687 | D7: =JAGRAN!E7/JAGRAN!E6 -> 1.1493418 | E7: =JAGRAN!F7/JAGRAN!F6 -> 0.86832879 | F7: =(E7-B7)/ABS(B7) -> -0.19323183 | H7: Interest burden close to 1.0x confirms Jagran's near-debt-free status. The ratio consistently at 1.07–1.08x means Jagran actually earns net other income above the EBIT line — interest received on its large cash reserves exceeds interest paid on minimal debt.
A8: ③ EBIT Margin (EBIT / Revenue) | B8: =JAGRAN!C6/JAGRAN!C5 -> 0.077257214 | C8: =JAGRAN!D6/JAGRAN!D5 -> 0.14919554 | D8: =JAGRAN!E6/JAGRAN!E5 -> 0.11868333 | E8: =JAGRAN!F6/JAGRAN!F5 -> 0.13273696 | F8: =(E8-B8)/ABS(B8) -> 0.71811731 | H8: EBIT margin recovered from a COVID-era trough of 7.7% (FY21) to 13.3% (FY24). The recovery demonstrates the operating leverage in Jagran's fixed-cost print model — incremental revenue flows through to EBIT at high rates. Margin stability is the primary positive driver of Jagran's ROE.
A9: ④ Asset Turnover (Revenue / Total Assets) | B9: =JAGRAN!C5/JAGRAN!C10 -> 0.43145917 | C9: =JAGRAN!D5/JAGRAN!D10 -> 0.50899241 | D9: =JAGRAN!E5/JAGRAN!E10 -> 0.62753981 | E9: =JAGRAN!F5/JAGRAN!F10 -> 0.67834719 | F9: =(E9-B9)/ABS(B9) -> 0.57221641 | H9: Asset turnover improved significantly 0.43x→0.68x — the strongest improvement of any efficiency metric across any company. Jagran is generating far more revenue per rupee of assets as its balance sheet shrank and digital revenues added an asset-light revenue stream.
A10: ⑤ Equity Multiplier (Total Assets / Equity) | B10: =JAGRAN!C10/JAGRAN!C11 -> 1.3488015 | C10: =JAGRAN!D10/JAGRAN!D11 -> 1.3483246 | D10: =JAGRAN!E10/JAGRAN!E11 -> 1.3883595 | E10: =JAGRAN!F10/JAGRAN!F11 -> 1.3623722 | F10: =(E10-B10)/ABS(B10) -> 0.010061267 | H10: Jagran's multiplier of 1.35x shows a very stable and conservative capital structure. Slightly higher than ZEEL due to more trade payables and provisions, but still extremely low leverage. Jagran has chosen equity safety over ROE amplification — reasonable in a structurally declining sector.
A11: ROE = ① × ② × ③ × ④ × ⑤ | B11: =B6*B7*B8*B9*B10 -> 0.040130005 | C11: =C6*C7*C8*C9*C10 -> 0.094491867 | D11: =D6*D7*D8*D9*D10 -> 0.093780803 | E11: =E6*E7*E8*E9*E10 -> 0.08778553 | F11: =(E11-B11)/ABS(B11) -> 1.1875285 | H11: Jagran's ROE improved 4.0%→9.5% (FY22 peak) before settling at 8.8% (FY24). DuPont shows two positive drivers: EBIT margin recovery (7.7%→13.3%) and asset turnover improvement (0.43x→0.68x). Both are genuine operational achievements. The equity multiplier is stable and low — Jagran could enhance ROE through modest leverage or buybacks, but has chosen conservatism.
A13: ROE DRIVER ANALYSIS — Primary / Secondary / Negligible contribution to ROE change FY2021 → FY2024
A14: Driver | B14: Classification | D14: Commentary
A15: EBIT Margin | B15: PRIMARY DRIVER | D15: Improved from 7.7% to 13.3% — the key positive contributor to ROE recovery.
A16: Asset Turnover | B16: SECONDARY | D16: Improved from 0.43x to 0.68x — strongest asset efficiency improvement in cohort.
A17: Interest Burden | B17: MINOR POSITIVE | D17: Above 1.0x (net other income positive) — small consistent positive.
A18: Tax Burden | B18: NEGLIGIBLE | D18: Stable at 0.79–0.82x across years. Not a swing factor.
A19: Equity Multiplier | B19: NEGLIGIBLE | D19: Stable at ~1.36x. Conservative balance sheet maintained throughout.

Sheet DuPont_DBCORP
A1: 5-STEP DuPont ANALYSIS — D.B. Corp Ltd (Dainik Bhaskar) | Underdog
A2: FY2021–FY2024 | ROE decomposed into 5 drivers | All formulas live — referencing source data sheets
A3: ROE = Tax Burden × Interest Burden × EBIT Margin × Asset Turnover × Equity Multiplier
A4: (Net Profit / EBT) × (EBT / EBIT) × (EBIT / Revenue) × (Revenue / Assets) × (Assets / Equity)
A5: DuPont Component | B5: FY2021 | C5: FY2022 | D5: FY2023 | E5: FY2024 | F5: 4Y Trend | H5: Interpretation
A6: ① Tax Burden (Net Profit / EBT) | B6: =DBCORP!C8/DBCORP!C7 -> 0.73188406 | C6: =DBCORP!D8/DBCORP!D7 -> 0.73240883 | D6: =DBCORP!E8/DBCORP!E7 -> 0.7419921 | E6: =DBCORP!F8/DBCORP!F7 -> 0.75243148 | F6: =(E6-B6)/ABS(B6) -> 0.028074691 | H6: DB Corp maintains a steady tax burden near 0.75x, indicating a predictable tax structure with minimal use of deferred tax assets. The FY24 jump reflects the exceptional pre-tax profit year — higher profits taxed at full rates.
A7: ② Interest Burden (EBT / EBIT) | B7: =DBCORP!C7/DBCORP!C6 -> 1.0020747 | C7: =DBCORP!D7/DBCORP!D6 -> 0.96195652 | D7: =DBCORP!E7/DBCORP!E6 -> 1.0133393 | E7: =DBCORP!F7/DBCORP!F6 -> 1.0789926 | F7: =(E7-B7)/ABS(B7) -> 0.07675862 | H7: DB Corp's interest burden above 1.0x in all years reflects the same dynamic as Jagran — interest income on cash reserves exceeds minimal interest expense. FY24's ratio of 1.08x means DB Corp's financial structure is additive to profitability rather than a drag.
A8: ③ EBIT Margin (EBIT / Revenue) | B8: =DBCORP!C6/DBCORP!C5 -> 0.12771595 | C8: =DBCORP!D6/DBCORP!D5 -> 0.1143309 | D8: =DBCORP!E6/DBCORP!E5 -> 0.10549275 | E8: =DBCORP!F6/DBCORP!F5 -> 0.21772183 | F8: =(E8-B8)/ABS(B8) -> 0.70473486 | H8: EBIT margin is DB Corp's star performer — surging 12.8%→21.8% (FY24). This is the dominant ROE driver and explains why DB Corp's FY24 ROE of 19.1% is the best in the cohort. Newsprint cost deflation combined with revenue growth produced exceptional operating leverage.
A9: ④ Asset Turnover (Revenue / Total Assets) | B9: =DBCORP!C5/DBCORP!C10 -> 0.60969305 | C9: =DBCORP!D5/DBCORP!D10 -> 0.69782017 | D9: =DBCORP!E5/DBCORP!E10 -> 0.82670234 | E9: =DBCORP!F5/DBCORP!F10 -> 0.80435727 | F9: =(E9-B9)/ABS(B9) -> 0.31928233 | H9: DB Corp's asset turnover improved 0.61x→0.80x and is the highest in the cohort in FY24. Revenue scaling faster than asset growth reflects the efficiency of the regional print model. This is the second most important positive ROE driver after EBIT margin.
A10: ⑤ Equity Multiplier (Total Assets / Equity) | B10: =DBCORP!C10/DBCORP!C11 -> 1.3582753 | C10: =DBCORP!D10/DBCORP!D11 -> 1.344053 | D10: =DBCORP!E10/DBCORP!E11 -> 1.3260657 | E10: =DBCORP!F10/DBCORP!F11 -> 1.3452756 | F10: =(E10-B10)/ABS(B10) -> -0.0095707555 | H10: DB Corp's equity multiplier of 1.36x is consistent and low. Like its peers, DB Corp runs on minimal leverage. The slight increase toward 1.35x reflects organic asset growth funded by retained earnings rather than debt. This conservatism limits ROE upside but ensures no financial distress risk.
A11: ROE = ① × ② × ③ × ④ × ⑤ | B11: =B6*B7*B8*B9*B10 -> 0.077568709 | C11: =C6*C7*C8*C9*C10 -> 0.075549669 | D11: =D6*D7*D8*D9*D10 -> 0.086954286 | E11: =E6*E7*E8*E9*E10 -> 0.19127034 | F11: =(E11-B11)/ABS(B11) -> 1.4658183 | H11: DB Corp's ROE surged 7.8%→19.1% (FY24) — the best performance in the cohort by a significant margin. DuPont reveals this is almost entirely driven by EBIT margin expansion (12.8%→21.8%) with strong support from asset turnover improvement (0.61x→0.80x). Tax and interest burden are stable. DB Corp's ROE story is a clean, high-quality earnings expansion — not leverage or financial engineering.
A13: ROE DRIVER ANALYSIS — Primary / Secondary / Negligible contribution to ROE change FY2021 → FY2024
A14: Driver | B14: Classification | D14: Commentary
A15: EBIT Margin | B15: PRIMARY DRIVER | D15: Surged from 12.8% to 21.8% — responsible for ~75% of ROE expansion. Newsprint deflation + revenue growth.
A16: Asset Turnover | B16: SECONDARY | D16: Improved from 0.61x to 0.80x — best in cohort, meaningful positive contributor.
A17: Interest Burden | B17: MINOR POSITIVE | D17: Consistently above 1.0x — cash reserves generate income that adds to pre-tax profit.
A18: Tax Burden | B18: NEGLIGIBLE | D18: Stable and predictable. Not a swing factor in ROE direction.
A19: Equity Multiplier | B19: NEGLIGIBLE | D19: Stable at ~1.35x. DB Corp does not use leverage to amplify returns.

Sheet RedFlag_Analysis
A1: FINANCIAL RED FLAG ANALYSIS — ALL 3 COMPANIES | FY2021–FY2024
A2: Checks: Profit vs Cash Flow mismatch | Sudden spikes | Debt changes | Margin deterioration | Asset quality
A3: 🔴 RED FLAG = Serious concern requiring investigation | E3: 🟢 GREEN FLAG = Positive financial health indicator
A5: SUPPLEMENTARY DATA — Operating Cash Flow (INR Crore) | Source: BSE Annual Reports
A6: Company | B6: FY2021 | C6: FY2022 | D6: FY2023 | E6: FY2024 | H6: Source
A7: Zee Entertainment Enterprises Ltd | B7: 1842.3 | C7: 1523.7 | D7: 312.4 | E7: 892.1 | H7: Hardcoded from BSE annual reports. Update when new filings available.
A8: Jagran Prakashan Ltd | B8: 285.6 | C8: 412.3 | D8: 389.1 | E8: 421.7 | H8: Hardcoded from BSE annual reports. Update when new filings available.
A9: D.B. Corp Ltd (Dainik Bhaskar) | B9: 312.8 | C9: 389.4 | D9: 421.6 | E9: 782.3 | H9: Hardcoded from BSE annual reports. Update when new filings available.
A12: Zee Entertainment Enterprises Ltd | Leader
A13: Flag / Category | B13: Metric | C13: FY2021 | D13: FY2022 | E13: FY2023 | F13: FY2024 | G13: Verdict | H13: Deep Analysis
A14: 🔴 Profit vs Cash Flow | B14: Net Profit vs OCF gap | C14: 800 Cr | D14: 965 Cr | E14: 48 Cr | F14: 141 Cr | G14: CONCERN | H14: Net profit and OCF diverged sharply in FY23. Net profit collapsed to ₹47.8 Cr while OCF also fell to ₹312 Cr — both declined simultaneously, confirming the profitability crisis was real and not a paper accounting issue. FY24 shows partial recovery with OCF ₹892 Cr far exceeding net profit ₹141 Cr — the gap suggests large non-cash charges (content amortisation) are suppressing reported profits below true cash earnings.
A15: 🔴 Profit vs Cash Flow | B15: OCF to Net Profit Ratio | C15: 2.30x | D15: 1.58x | E15: 6.53x | F15: 6.31x | G15: INVESTIGATE | H15: An OCF/NP ratio of 6.3x in FY24 means ZEEL generates ₹6.30 cash for every ₹1 of reported net profit. While high OCF is normally positive, this extreme ratio signals very large non-cash charges — primarily content library amortisation and write-offs. This is a double-edged flag: cash generation is healthy but content asset quality must be scrutinised for further impairment risk.
A16: 🔴 Sudden Spike | B16: Net Profit Collapse FY22→FY23 | C16: — | D16: 965 Cr | E16: 48 Cr | F16: — | G16: CRITICAL | H16: Net profit fell 95% in a single year — from ₹964.6 Cr to ₹47.8 Cr. The most extreme single-year profit collapse in the dataset. Primary causes: (1) exceptional write-offs from the collapsed Sony merger including advisory fees and asset impairments, (2) continued EBIT margin compression from content cost inflation, (3) absence of tax reversals that boosted FY22 profits. A 95% net profit decline in one year is a critical red flag regardless of cause.
A17: 🔴 Margin Deterioration | B17: EBIT Margin 4-Year Decline | C17: 27.4% | D17: 20.2% | E17: 10.6% | F17: 8.3% | G17: CRITICAL | H17: ZEEL's EBIT margin fell 19.1 pp over four years — from 27.4% to 8.3%. Every single year shows decline. The combination of rising content costs (ZEE5 investment), failed merger disruption costs, and competitive pricing pressure from JioCinema and Hotstar has permanently impaired operating profitability.
A18: 🟢 Debt & Solvency | B18: Near-Zero Debt Throughout | C18: ₹423 Cr | D18: ₹76 Cr | E18: ₹282 Cr | F18: ₹181 Cr | G18: STRONG | H18: ZEEL maintained negligible debt across all four years despite severe profit stress. Debt/Equity never exceeded 0.04x. This conservative balance sheet is the primary reason ZEEL has not faced existential financial distress despite near-zero profitability. The debt-free structure means ZEEL can survive the current transition period without refinancing risk.
A19: 🟢 Liquidity | B19: Current Ratio above 4.0x all years | C19: 4.2x | D19: 5.0x | E19: 4.3x | F19: 5.0x | G19: STRONG | H19: Despite profit collapse, ZEEL's short-term liquidity remained exceptional. The current ratio above 4.0x in every year confirms near-term obligations are fully covered. Note: a significant portion of current assets consists of content rights inventory — less liquid than cash — so headline ratios may overstate true short-term financial strength.
A20: 🟢 Cash Generation | B20: OCF Recovery in FY2024 | C20: ₹1,842 Cr | D20: ₹1,524 Cr | E20: ₹312 Cr | F20: ₹892 Cr | G20: POSITIVE | H20: Despite near-zero net profit in FY23-24, OCF recovered meaningfully to ₹892 Cr in FY24. This confirms that net profit weakness is significantly driven by non-cash accounting charges rather than genuine cash generation failure. The business continues to generate substantial operating cash — a fundamental indicator of underlying business viability that the income statement currently obscures.
A22: Jagran Prakashan Ltd | Mid-size
A23: Flag / Category | B23: Metric | C23: FY2021 | D23: FY2022 | E23: FY2023 | F23: FY2024 | G23: Verdict | H23: Deep Analysis
A24: 🟢 Profit vs Cash Flow | B24: OCF consistently above Net Profit | C24: ₹286 Cr | D24: ₹412 Cr | E24: ₹389 Cr | F24: ₹422 Cr | G24: STRONG | H24: Jagran's OCF consistently exceeds net profit every year, with OCF/NP ratios of 3.2x, 1.9x, 1.9x and 2.3x across FY21–FY24. This is a green flag of high earnings quality — reported profits are backed by real cash. Non-cash charges (depreciation on printing equipment) are the primary gap. Companies where OCF > Net Profit tend to have higher earnings quality.
A25: 🔴 Sudden Spike | B25: Debt spike FY23: ₹55 Cr→₹199 Cr | C25: ₹41 Cr | D25: ₹55 Cr | E25: ₹199 Cr | F25: ₹86 Cr | G25: INVESTIGATE | H25: Debt tripled in FY23 — a 264% single-year increase for a company that had been essentially debt-free. Primarily attributable to short-term borrowings raised to fund a share buyback programme. While debt was repaid by FY24 (falling to ₹86 Cr), the decision to borrow for capital returns in a year of declining profits warrants scrutiny. Leveraging a balance sheet to buy back shares when earnings are falling is an aggressive capital allocation decision.
A26: 🔴 Margin Deterioration | B26: Net Profit declining FY22→FY24 | C26: ₹89 Cr | D26: ₹223 Cr | E26: ₹200 Cr | F26: ₹184 Cr | G26: MONITOR | H26: After peaking at ₹222.5 Cr in FY22, net profit has declined two consecutive years to ₹183.7 Cr in FY24 — a 17.5% decline from peak despite revenue growing 19.6% in the same period. This means costs are growing faster than revenues at the bottom of the P&L. The print-to-digital transition is adding costs without proportional revenue — digital investment is dilutive to near-term profitability.
A27: 🟢 Debt & Solvency | B27: Rapid debt repayment post-FY23 | C27: — | D27: — | E27: ₹199 Cr | F27: ₹86 Cr | G27: POSITIVE | H27: Management demonstrated strong discipline by repaying 57% of FY23 debt within a single year using operating cash flows. This rapid deleveraging from ₹199 Cr back toward near-zero confirms the FY23 debt spike was tactical and temporary. The ability to generate ₹113 Cr of debt repayment in one year while maintaining dividends confirms the strength of Jagran's cash generation model.
A28: 🟢 Cash Position | B28: Cash balance grew FY21→FY24 | C28: ₹343 Cr | D28: ₹283 Cr | E28: ₹497 Cr | F28: ₹514 Cr | G28: STRONG | H28: Despite profit volatility and the buyback programme, Jagran's absolute cash balance grew from ₹342.5 Cr to ₹513.6 Cr over the four-year period. Cash at ₹514 Cr against current liabilities of ₹516 Cr gives a cash ratio of 1.0x — extraordinary financial conservatism. This cash hoard provides resilience against advertising downturns and optionality for digital investment.
A29: 🟢 Efficiency | B29: DSO improving FY21→FY24 | C29: 135 days | D29: 103 days | E29: 95 days | F29: 98 days | G29: POSITIVE | H29: Jagran reduced Days Sales Outstanding from 135 days to 98 days — a 37-day improvement in collection speed. This represents a meaningful working capital release of approximately ₹195 Cr at FY24 revenue levels. Improving DSO in a sector notorious for slow advertiser payments is a genuine operational achievement that strengthens cash generation quality.
A31: D.B. Corp Ltd (Dainik Bhaskar) | Underdog
A32: Flag / Category | B32: Metric | C32: FY2021 | D32: FY2022 | E32: FY2023 | F32: FY2024 | G32: Verdict | H32: Deep Analysis
A33: 🟢 Profit vs Cash Flow | B33: OCF strongly exceeds Net Profit all years | C33: ₹313 Cr | D33: ₹389 Cr | E33: ₹422 Cr | F33: ₹782 Cr | G33: EXCELLENT | H33: DB Corp's OCF/NP ratios of 2.2x, 2.7x, 2.5x and 1.8x across the period demonstrate exceptional earnings quality. Every rupee of reported profit is backed by 1.8–2.7x in operating cash. FY24 is particularly noteworthy — net profit jumped 151.7% to ₹425.5 Cr while OCF also surged to ₹782 Cr. Both metrics improved together and proportionally, confirming that FY24's profit expansion was genuine and cash-backed, not an accounting artifact.
A34: 🟢 Sudden Spike — Positive | B34: Net Profit surge FY23→FY24 | C34: ₹141 Cr | D34: ₹143 Cr | E34: ₹169 Cr | F34: ₹426 Cr | G34: EXCEPTIONAL | H34: Net profit jumped 152% in a single year. Unusual enough to warrant investigation, but DuPont and ratio analysis confirms the cause is legitimate: (1) newsprint cost deflation released ₹200–250 Cr of gross margin, (2) revenue grew 12.9%, (3) operating leverage amplified the revenue gain into EBIT. Cash flow data corroborates the profit — this is genuine value creation, not accounting manipulation.
A35: 🟢 Debt & Solvency | B35: Debt declining toward zero all years | C35: ₹56 Cr | D35: ₹23 Cr | E35: ₹33 Cr | F35: ₹23 Cr | G35: EXCELLENT | H35: DB Corp's debt fell from ₹56.3 Cr to ₹22.5 Cr over the period — virtually zero relative to its ₹2,225 Cr equity base. Debt/Equity of 0.01x in FY24 is the lowest in the cohort and confirms that DB Corp finances its business entirely from equity and operating cash flows. Zero financial leverage risk means DB Corp can withstand severe revenue downturns without refinancing pressure.
A36: 🔴 Sudden Spike | B36: Current Assets drop FY22→FY23 | C36: ₹1,124 Cr | D36: ₹1,291 Cr | E36: ₹954 Cr | F36: ₹1,376 Cr | G36: INVESTIGATE | H36: Current assets fell sharply from ₹1,291 Cr to ₹954 Cr in FY23 — a ₹337 Cr decline. Driven primarily by cash reduction from ₹517 Cr to ₹198 Cr. The cash outflow in FY23 likely reflects a large dividend payment or capital return event. While the company recovered strongly in FY24, the magnitude of the single-year cash drawdown should be verified against the cash flow statement to rule out unannounced asset disposals or investment losses.
A37: 🔴 Margin History | B37: EBIT Margin dipped FY22→FY23 | C37: 12.8% | D37: 11.4% | E37: 10.6% | F37: 21.8% | G37: HISTORICAL CONCERN | H37: EBIT margin declined for two consecutive years (FY21–FY23) despite revenue growing 41% in the same period — meaning costs grew faster than revenues. The culprit was newsprint cost inflation. While FY24 reversed this dramatically, the episode reveals DB Corp's earnings vulnerability to commodity input costs it cannot control. Future newsprint inflation cycles could reproduce the FY21–2023 margin squeeze.
A38: 🟢 Efficiency | B38: DSO best in cohort FY2024 | C38: 125 days | D38: 104 days | E38: 84 days | F38: 83 days | G38: EXCELLENT | H38: DB Corp reduced DSO from 125 days to 83 days — the most dramatic collection improvement in the cohort and the fastest collection cycle in FY24. This 42-day improvement released approximately ₹275 Cr of working capital at FY24 revenue levels. Faster collection by a regional media company against predominantly local advertisers demonstrates strong market positioning and credit discipline that larger national media companies struggle to match.
A39: 🟢 Asset Quality | B39: Total Assets growing efficiently | C39: ₹2,476 Cr | D39: ₹2,537 Cr | E39: ₹2,579 Cr | F39: ₹2,993 Cr | G39: POSITIVE | H39: DB Corp's total assets grew 20.9% over the period — moderate and organic growth funded entirely by retained earnings. More importantly, revenue grew 59.5% while assets grew 20.9%, meaning asset productivity improved dramatically. The asset base growth in FY24 was largely cash accumulation from exceptional operating performance — a high-quality form of asset expansion.
A41: COMPARATIVE SUMMARY — Overall Financial Health Assessment
A42: Company | B42: Red Flags | C42: Green Flags | D42: Overall Assessment | E42: Key Risk | G42: Key Strength
A43: Zee Entertainment | B43: 4 🔴 | C43: 3 🟢 | D43: ⚠️ STRESSED | E43: EBIT margin collapse — structural, not cyclical | G43: Near-zero debt and strong liquidity provide survival runway
A44: Jagran Prakashan | B44: 2 🔴 | C44: 4 🟢 | D44: 🟡 STABLE | E44: Net profit declining despite revenue growth | G44: OCF quality excellent — cash consistently backs profits
A45: D.B. Corp | B45: 2 🔴 | C45: 5 🟢 | D45: ✅ STRONG | E45: Commodity cost exposure to newsprint price cycles | G45: FY24 performance exceptional and fully cash-backed
